roach_bsp/dev/modules/epb_wb_bridge_reg/hdl/epb_wb_bridge_reg.v
`timescale 1ns/10ps

module epb_wb_bridge_reg(
    wb_clk_i, wb_rst_i,
    wb_cyc_o, wb_stb_o, wb_we_o, wb_sel_o,
    wb_adr_o, wb_dat_o, wb_dat_i,
    wb_ack_i, wb_err_i,

    epb_clk,
    epb_cs_n, epb_r_w_n, epb_oe_n, epb_be_n, 
    epb_addr, epb_addr_gb,
    epb_data_i, epb_data_o,
    epb_rdy
  );
  input  wb_clk_i, wb_rst_i;
  output wb_cyc_o, wb_stb_o, wb_we_o;
  output  [1:0] wb_sel_o;
  output [31:0] wb_adr_o;
  output [15:0] wb_dat_o;
  input  [15:0] wb_dat_i;
  input  wb_ack_i, wb_err_i;

  input  epb_clk;
  input  epb_cs_n, epb_r_w_n, epb_oe_n;
  input   [1:0] epb_be_n;
  input  [22:0] epb_addr;
  input   [5:0] epb_addr_gb;
  input  [15:0] epb_data_i;
  output [15:0] epb_data_o;
  output epb_rdy;

  /******* Common Signals *******/

  reg cmnd_got, cmnd_ack;
  reg resp_got, resp_ack;

  wire cmnd_got_unstable, cmnd_ack_unstable;
  wire resp_got_unstable, resp_ack_unstable;

  /******* EPB Bus control ******/

  reg cmnd_got_reg;
  assign cmnd_got_unstable = prev_cs_n != epb_cs_n && !epb_cs_n | cmnd_got_reg; 
  reg prev_cs_n; 

  /* Command Generation */
  always @(posedge epb_clk) begin
    prev_cs_n <= epb_cs_n;
    if (wb_rst_i) begin
      cmnd_got_reg <= 1'b0;
    end else begin
      if (prev_cs_n != epb_cs_n && !epb_cs_n) begin
        cmnd_got_reg <= 1'b1;
      end

      if (cmnd_ack) begin
        cmnd_got_reg <= 1'b0;
      end
    end
  end

  /* Response Collection */

  reg resp_ack_reg;
  assign resp_ack_unstable = resp_ack_reg | resp_got;

  reg epb_rdy;

  always @(posedge wb_clk_i) begin
    if (wb_rst_i) begin
      resp_ack_reg <= 1'b0;
      epb_rdy <= 1'b0;
    end else begin
      if (cmnd_got_unstable) begin
        epb_rdy <= 1'b0;
      end
      if (resp_got) begin
        if (~resp_ack_reg) begin
          epb_rdy <= 1'b1;
        end
        resp_ack_reg <= 1'b1;
      end else begin
        resp_ack_reg <= 1'b0;
      end
    end
  end

  /**** WishBone Generation ****/
  reg [15:0] wb_dat_i_reg;
  assign epb_data_o = wb_dat_i_reg;
  assign wb_dat_o   = epb_data_i;
  assign wb_adr_o   = {2'b0, epb_addr_gb, epb_addr, 1'b0};
  assign wb_sel_o   = ~epb_be_n;
  assign wb_we_o    = ~epb_r_w_n;

  /* Register Data */
  always @(posedge wb_clk_i) begin
    if (wb_ack_i) begin
      wb_dat_i_reg <= wb_dat_i;
    end
  end

  /* Command collection */

  reg wb_cyc_o;
  assign wb_stb_o = wb_cyc_o;

  reg cmnd_ack_reg;
  assign cmnd_ack_unstable = cmnd_ack_reg | cmnd_got;

  always @(posedge wb_clk_i) begin
    //strobes
    wb_cyc_o <= 1'b0;
    if (wb_rst_i) begin
      cmnd_ack_reg <= 1'b0;
    end else begin
      if (cmnd_got) begin
        if (~cmnd_ack_reg) begin //on first
          wb_cyc_o <= 1'b1;
        end
        cmnd_ack_reg <= 1'b1;
      end else begin
        cmnd_ack_reg <= 1'b0;
      end
    end
  end

  /* Response generation */
  reg resp_got_reg;
  assign resp_got_unstable = wb_ack_i | resp_got_reg;

  always @(posedge wb_clk_i) begin
    if (wb_rst_i) begin
      resp_got_reg <= 1'b0;
    end else begin
      if (wb_ack_i || wb_err_i) begin
        resp_got_reg <= 1'b1;
      end
      if (resp_ack) begin
        resp_got_reg <= 1'b0;
      end
    end
  end

  /******** Clock Domain Crossing **********/

  reg resp_got_retimed;
  always @(posedge epb_clk) begin
    resp_got_retimed <= resp_got_unstable;
    resp_got         <= resp_got_retimed;
  end
  //synthesis attribute USET of resp_got_retimed is SET0
  //synthesis attribute USET of resp_got         is SET0
  //synthesis attribute RLOC of resp_got_retimed is R0C0
  //synthesis attribute RLOC of resp_got         is R0C1

  reg resp_ack_retimed;
  always @(posedge wb_clk_i) begin
    resp_ack_retimed <= resp_ack_unstable;
    resp_ack         <= resp_ack_retimed;
  end
  //synthesis attribute USET of resp_ack_retimed is SET1
  //synthesis attribute USET of resp_ack         is SET1
  //synthesis attribute RLOC of resp_ack_retimed is R0C0
  //synthesis attribute RLOC of resp_ack         is R0C1

  reg cmnd_got_retimed;
  always @(posedge wb_clk_i) begin
    cmnd_got_retimed <= cmnd_got_unstable;
    cmnd_got         <= cmnd_got_retimed;
  end
  //synthesis attribute USET of cmnd_got_retimed is SET2
  //synthesis attribute USET of cmnd_got         is SET2
  //synthesis attribute RLOC of cmnd_got_retimed is R0C0
  //synthesis attribute RLOC of cmnd_got         is R0C1

  reg cmnd_ack_retimed;
  always @(posedge epb_clk) begin
    cmnd_ack_retimed <= cmnd_ack_unstable;
    cmnd_ack         <= cmnd_ack_retimed;
  end
  //synthesis attribute USET of cmnd_ack_retimed is SET3
  //synthesis attribute USET of cmnd_ack         is SET3
  //synthesis attribute RLOC of cmnd_ack_retimed is R0C0
  //synthesis attribute RLOC of cmnd_ack         is R0C1

endmodule

roach_bsp/dev/modules/epb_wb_bridge_reg/tb/hdl/TB_epb_wb_bridge_reg.v
`timescale 1ns/10ps

`define SIMLENGTH 64000
`define CLK_PERIOD 10

`define NUM_OPS 16
module TB_epb_wb_bridge_reg();
  reg reset;
  wire clk;

  wire wb_cyc_o, wb_stb_o, wb_we_o;
  wire  [1:0] wb_sel_o;
  wire [31:0] wb_adr_o;
  wire [15:0] wb_dat_o;
  reg  [15:0] wb_dat_i;
  reg  wb_ack_i, wb_err_i;

  wire epb_clk;
  reg  epb_cs_n;
  reg  epb_r_w_n;
  wire epb_oe_n;
  wire  [1:0] epb_be_n;
  wire [22:0] epb_addr;
  wire  [5:0] epb_addr_gb;
  wire [15:0] epb_data_o;
  reg  [15:0] epb_data_i;
  wire epb_rdy;

  epb_wb_bridge_reg epb_wb_bridge_reg_inst(
    .wb_clk_i(clk), .wb_rst_i(reset),
    .wb_cyc_o(wb_cyc_o), .wb_stb_o(wb_stb_o), .wb_we_o(wb_we_o), .wb_sel_o(wb_sel_o),
    .wb_adr_o(wb_adr_o), .wb_dat_o(wb_dat_o), .wb_dat_i(wb_dat_i),
    .wb_ack_i(wb_ack_i), .wb_err_i(wb_err_i),

    .epb_clk(epb_clk),
    .epb_cs_n(epb_cs_n), .epb_r_w_n(epb_r_w_n), .epb_oe_n(epb_oe_n), .epb_be_n(epb_be_n), 
    .epb_addr(epb_addr), .epb_addr_gb(epb_addr_gb),
    .epb_data_i(epb_data_i), .epb_data_o(epb_data_o), 
    .epb_rdy(epb_rdy)
  );

  reg [31:0] clk_counter;

  initial begin
    $dumpvars;
    reset<=1'b1;
    clk_counter<=32'b0;
    #50
    reset<=1'b0;
`ifdef DEBUG
    $display("sys: reset cleared");
`endif
    #`SIMLENGTH
    $display("FAILED: simulation timed out");
    $finish;
  end

  assign clk = clk_counter < ((`CLK_PERIOD) / 2);

  always begin
    #1 clk_counter <= (clk_counter == `CLK_PERIOD - 1 ? 32'b0 : clk_counter + 1);
  end

  /****** Mode Control *******/
  reg [15:0] wb_mem  [1024*64-1:0]; 
  reg [15:0] epb_mem [1024*64-1:0]; 

  reg mode;
  localparam MODE_WRITE = 1'd0;
  localparam MODE_READ  = 1'd1;
  reg [1:0] mode_done;

  integer i;
  always @(posedge clk) begin
    if (reset) begin
      mode <= MODE_WRITE;
    end else begin
      case (mode)
        MODE_WRITE: begin
          if (mode_done[MODE_WRITE]) begin
            mode <= MODE_READ;
`ifdef DEBUG
            $display("mode: MODE_WRITE done");
`endif 
          end
        end
        MODE_READ: begin
          if (mode_done[MODE_READ]) begin
            for (i=0; i < `NUM_OPS; i=i+1) begin
              if (wb_mem[i] !== i) begin
                $display("FAILED: wb mem mismatch - got %x, expected %x", wb_mem[i], i);
                $finish;
              end
              if (epb_mem[i] !== i) begin
                $display("FAILED: epb mem mismatch - got %x, expected %x", epb_mem[i], i);
                $finish;
              end
            end
            $display("PASSED");
            $finish;
          end
        end
      endcase
    end
  end

  /*********** WishBone Slave ************/

  always @(posedge clk) begin
    wb_ack_i <= 1'b0;
    if (reset) begin
    end else begin
      if (wb_cyc_o & wb_stb_o & !wb_ack_i) begin
        wb_ack_i <= 1'b1;
        if (wb_we_o) begin
          wb_mem[wb_adr_o[15:1]] <= wb_dat_o;
`ifdef DEBUG
          $display("wbs: got write, adr = %x, data = %x", wb_adr_o, wb_dat_o);
`endif
        end else begin
          wb_dat_i <= wb_mem[wb_adr_o[15:1]];
`ifdef DEBUG
          $display("wbs: got read, adr = %x, data = %x", wb_adr_o, wb_mem[wb_adr_o[15:1]]);
`endif
        end
      end
    end
  end

  /************ EPB Master *****************/

  reg clk_div;
  initial begin
    clk_div <= 1'b0;
  end
  always @(posedge clk) begin
    clk_div <= ~clk_div;
  end

  assign #1 epb_clk = clk_div;

  reg [1:0] epb_state;
  localparam EPB_COMMAND = 2'd0;
  localparam EPB_COLLECT = 2'd1;
  localparam EPB_WAIT    = 2'd2;

  reg [31:0] mode_progress;

  reg [28:0] epb_addr_r;
  assign epb_addr = epb_addr_r[22:0];
  assign epb_addr_gb = epb_addr_r[28:23];

  assign epb_oe_n = epb_cs_n;

  assign epb_be_n = 2'b00;

  always @(posedge epb_clk) begin
    if (reset) begin
      epb_state <= EPB_COMMAND;
      mode_progress <= 32'b0;
      epb_cs_n <= 1'b1;
      mode_done[MODE_WRITE] <= 1'b0;
      mode_done[MODE_READ]  <= 1'b0;
    end else begin
      case (epb_state) 
        EPB_COMMAND: begin
          case (mode)
            MODE_WRITE: begin
              epb_r_w_n <= 1'b0;
`ifdef DEBUG
              $display("epbm: sent write, adr = %x, data = %x", mode_progress[28:0], mode_progress[15:0]);
`endif
            end
            MODE_READ: begin
              epb_r_w_n <= 1'b1;
`ifdef DEBUG
              $display("epbm: sent read, adr = %x", mode_progress[28:0]);
`endif
            end
          endcase

          epb_cs_n <= 1'b0;
          epb_addr_r <= mode_progress[28:0];
          epb_data_i <= mode_progress[15:0];

          epb_state  <= EPB_COLLECT;
        end
        EPB_COLLECT: begin
          if (epb_rdy) begin
            epb_cs_n <= 1'b1;
            if (mode_progress < `NUM_OPS - 1) begin
              mode_progress <= mode_progress + 1;
              epb_state <= EPB_COMMAND;
            end else begin
              mode_progress <= 32'b0;
              mode_done[mode] <= 1'b1;
              epb_state <= EPB_WAIT;
            end
            if (mode == MODE_READ) begin
              epb_mem[epb_addr_r] <= epb_data_o;
            end
          end
        end
        EPB_WAIT: begin
          epb_state <= EPB_COMMAND;
        end
      endcase
    end
  end

  
endmodule

roach_bsp/dev/modules/epb_wb_bridge_reg/tb/dump.vcd
$date
	Wed Apr 16 15:40:16 2008
$end
$version
	Icarus Verilog
$end
$timescale
	10ps
$end
$scope module TB_epb_wb_bridge_reg $end
$var wire 1 ! clk $end
$var wire 23 " epb_addr [22:0] $end
$var wire 6 # epb_addr_gb [5:0] $end
$var wire 2 $ epb_be_n [1:0] $end
$var wire 1 % epb_clk $end
$var wire 16 & epb_data_o [15:0] $end
$var wire 1 ' epb_oe_n $end
$var wire 1 ( epb_rdy $end
$var wire 32 ) wb_adr_o [31:0] $end
$var wire 1 * wb_cyc_o $end
$var wire 16 + wb_dat_o [15:0] $end
$var wire 2 , wb_sel_o [1:0] $end
$var wire 1 - wb_stb_o $end
$var wire 1 . wb_we_o $end
$var reg 32 / clk_counter [31:0] $end
$var reg 1 0 clk_div $end
$var reg 29 1 epb_addr_r [28:0] $end
$var reg 1 2 epb_cs_n $end
$var reg 16 3 epb_data_i [15:0] $end
$var reg 1 4 epb_r_w_n $end
$var reg 2 5 epb_state [1:0] $end
$var reg 32 6 i [31:0] $end
$var reg 1 7 mode $end
$var reg 2 8 mode_done [1:0] $end
$var reg 32 9 mode_progress [31:0] $end
$var reg 1 : reset $end
$var reg 1 ; wb_ack_i $end
$var reg 16 < wb_dat_i [15:0] $end
$var reg 1 = wb_err_i $end
$scope module epb_wb_bridge_reg_inst $end
$var wire 1 > cmnd_ack_unstable $end
$var wire 1 ? cmnd_got_unstable $end
$var wire 23 @ epb_addr [22:0] $end
$var wire 6 A epb_addr_gb [5:0] $end
$var wire 2 B epb_be_n [1:0] $end
$var wire 1 % epb_clk $end
$var wire 1 C epb_cs_n $end
$var wire 16 D epb_data_i [15:0] $end
$var wire 16 E epb_data_o [15:0] $end
$var wire 1 ' epb_oe_n $end
$var wire 1 F epb_r_w_n $end
$var wire 1 G resp_ack_unstable $end
$var wire 1 H resp_got_unstable $end
$var wire 1 I wb_ack_i $end
$var wire 32 J wb_adr_o [31:0] $end
$var wire 1 ! wb_clk_i $end
$var wire 16 K wb_dat_i [15:0] $end
$var wire 16 L wb_dat_o [15:0] $end
$var wire 1 M wb_err_i $end
$var wire 1 N wb_rst_i $end
$var wire 2 O wb_sel_o [1:0] $end
$var wire 1 - wb_stb_o $end
$var wire 1 . wb_we_o $end
$var reg 1 P cmnd_ack $end
$var reg 1 Q cmnd_ack_reg $end
$var reg 1 R cmnd_ack_retimed $end
$var reg 1 S cmnd_got $end
$var reg 1 T cmnd_got_reg $end
$var reg 1 U cmnd_got_retimed $end
$var reg 1 V epb_rdy $end
$var reg 1 W prev_cs_n $end
$var reg 1 X resp_ack $end
$var reg 1 Y resp_ack_reg $end
$var reg 1 Z resp_ack_retimed $end
$var reg 1 [ resp_got $end
$var reg 1 \ resp_got_reg $end
$var reg 1 ] resp_got_retimed $end
$var reg 1 ^ wb_cyc_o $end
$var reg 16 _ wb_dat_i_reg [15:0] $end
$upscope $end
$upscope $end
$enddefinitions $end
#0
$dumpvars
bx _
0^
x]
0\
x[
xZ
0Y
xX
xW
0V
xU
xT
xS
xR
0Q
xP
b11 O
1N
xM
bx L
bx K
b0xxxxxxxxxxxxxxxxxxxxxxxxxxxxx0 J
0I
0H
xG
xF
bx E
bx D
xC
b0 B
bx A
bx @
x?
x>
x=
bx <
0;
1:
bx 9
bx 8
07
bx 6
bx 5
x4
bx 3
x2
bx 1
10
b0 /
x.
0-
b11 ,
bx +
0*
b0xxxxxxxxxxxxxxxxxxxxxxxxxxxxx0 )
0(
x'
bx &
x%
b0 $
bx #
bx "
1!
$end
#100
0?
0T
0]
b0 8
12
1C
1'
b0 9
b0 5
b1 /
1%
#200
b10 /
#300
b11 /
#400
b100 /
#500
b101 /
0!
#600
b110 /
#700
b111 /
#800
b1000 /
#900
b1001 /
#1000
00
0U
b0 /
1!
#1100
b1 /
0%
#1200
b10 /
#1300
b11 /
#1400
b100 /
#1500
b101 /
0!
#1600
b110 /
#1700
b111 /
#1800
b1000 /
#1900
b1001 /
#2000
0>
0S
10
b0 /
1!
#2100
0G
b0 8
0R
0[
1W
b1 /
1%
#2200
b10 /
#2300
b11 /
#2400
b100 /
#2500
b101 /
0!
#2600
b110 /
#2700
b111 /
#2800
b1000 /
#2900
b1001 /
#3000
00
0Z
b0 /
1!
#3100
b1 /
0%
#3200
b10 /
#3300
b11 /
#3400
b100 /
#3500
b101 /
0!
#3600
b110 /
#3700
b111 /
#3800
b1000 /
#3900
b1001 /
#4000
0X
10
b0 /
1!
#4100
0P
b0 8
b1 /
1%
#4200
b10 /
#4300
b11 /
#4400
b100 /
#4500
b101 /
0!
#4600
b110 /
#4700
b111 /
#4800
b1000 /
#4900
b1001 /
#5000
00
b0 /
1!
0:
0N
#5100
b1 /
0%
#5200
b10 /
#5300
b11 /
#5400
b100 /
#5500
b101 /
0!
#5600
b110 /
#5700
b111 /
#5800
b1000 /
#5900
b1001 /
#6000
10
b0 /
1!
#6100
1?
b0 "
b0 @
b0 )
b0 J
b0 #
b0 A
1.
b1 5
b0 3
b0 +
b0 D
b0 L
b0 1
02
0C
0'
04
0F
b1 /
1%
#6200
b10 /
#6300
b11 /
#6400
b100 /
#6500
b101 /
0!
#6600
b110 /
#6700
b111 /
#6800
b1000 /
#6900
b1001 /
#7000
00
1U
b0 /
1!
#7100
b1 /
0%
#7200
b10 /
#7300
b11 /
#7400
b100 /
#7500
b101 /
0!
#7600
b110 /
#7700
b111 /
#7800
b1000 /
#7900
b1001 /
#8000
1>
1S
10
b0 /
1!
#8100
0?
1T
0W
1R
b1 /
1%
#8200
b10 /
#8300
b11 /
#8400
b100 /
#8500
b101 /
0!
#8600
b110 /
#8700
b111 /
#8800
b1000 /
#8900
b1001 /
#9000
00
0U
1Q
1^
1-
1*
b0 /
1!
#9100
b1 /
0%
#9200
b10 /
#9300
b11 /
#9400
b100 /
#9500
b101 /
0!
#9600
b110 /
#9700
b111 /
#9800
b1000 /
#9900
b1001 /
#10000
1H
0^
0-
0*
0S
1;
1I
10
b0 /
1!
#10100
1P
1]
b1 /
1%
#10200
b10 /
#10300
b11 /
#10400
b100 /
#10500
b101 /
0!
#10600
b110 /
#10700
b111 /
#10800
b1000 /
#10900
b1001 /
#11000
0>
00
0;
0I
1\
0Q
b0 /
1!
#11100
b1 /
0%
#11200
b10 /
#11300
b11 /
#11400
b100 /
#11500
b101 /
0!
#11600
b110 /
#11700
b111 /
#11800
b1000 /
#11900
b1001 /
#12000
10
b0 /
1!
#12100
1G
0T
1[
0R
b1 /
1%
#12200
b10 /
#12300
b11 /
#12400
b100 /
#12500
b101 /
0!
#12600
b110 /
#12700
b111 /
#12800
b1000 /
#12900
b1001 /
#13000
00
1Z
1Y
1V
1(
b0 /
1!
#13100
b1 /
0%
#13200
b10 /
#13300
b11 /
#13400
b100 /
#13500
b101 /
0!
#13600
b110 /
#13700
b111 /
#13800
b1000 /
#13900
b1001 /
#14000
1X
10
b0 /
1!
#14100
b0 5
b1 9
12
1C
1'
0P
b1 /
1%
#14200
b10 /
#14300
b11 /
#14400
b100 /
#14500
b101 /
0!
#14600
b110 /
#14700
b111 /
#14800
b1000 /
#14900
b1001 /
#15000
0H
00
0\
b0 /
1!
#15100
b1 /
0%
#15200
b10 /
#15300
b11 /
#15400
b100 /
#15500
b101 /
0!
#15600
b110 /
#15700
b111 /
#15800
b1000 /
#15900
b1001 /
#16000
10
b0 /
1!
#16100
1?
b10 )
b10 J
b1 "
b1 @
1W
0]
b1 5
b1 3
b1 +
b1 D
b1 L
b1 1
02
0C
0'
b1 /
1%
#16200
b10 /
#16300
b11 /
#16400
b100 /
#16500
b101 /
0!
#16600
b110 /
#16700
b111 /
#16800
b1000 /
#16900
b1001 /
#17000
00
1U
0V
0(
b0 /
1!
#17100
b1 /
0%
#17200
b10 /
#17300
b11 /
#17400
b100 /
#17500
b101 /
0!
#17600
b110 /
#17700
b111 /
#17800
b1000 /
#17900
b1001 /
#18000
1>
1S
10
b0 /
1!
#18100
0?
1R
0[
1T
0W
b1 /
1%
#18200
b10 /
#18300
b11 /
#18400
b100 /
#18500
b101 /
0!
#18600
b110 /
#18700
b111 /
#18800
b1000 /
#18900
b1001 /
#19000
0G
00
0U
1Q
1^
1-
1*
0Y
b0 /
1!
#19100
b1 /
0%
#19200
b10 /
#19300
b11 /
#19400
b100 /
#19500
b101 /
0!
#19600
b110 /
#19700
b111 /
#19800
b1000 /
#19900
b1001 /
#20000
1H
0^
0-
0*
0Z
0S
1;
1I
10
b0 /
1!
#20100
1]
1P
b1 /
1%
#20200
b10 /
#20300
b11 /
#20400
b100 /
#20500
b101 /
0!
#20600
b110 /
#20700
b111 /
#20800
b1000 /
#20900
b1001 /
#21000
0H
0>
00
0;
0I
0X
0\
0Q
b0 /
1!
#21100
b1 /
0%
#21200
b10 /
#21300
b11 /
#21400
b100 /
#21500
b101 /
0!
#21600
b110 /
#21700
b111 /
#21800
b1000 /
#21900
b1001 /
#22000
10
b0 /
1!
#22100
1G
0R
1[
0]
0T
b1 /
1%
#22200
b10 /
#22300
b11 /
#22400
b100 /
#22500
b101 /
0!
#22600
b110 /
#22700
b111 /
#22800
b1000 /
#22900
b1001 /
#23000
00
1Z
1Y
1V
1(
b0 /
1!
#23100
b1 /
0%
#23200
b10 /
#23300
b11 /
#23400
b100 /
#23500
b101 /
0!
#23600
b110 /
#23700
b111 /
#23800
b1000 /
#23900
b1001 /
#24000
1X
10
b0 /
1!
#24100
0[
0P
b0 5
b10 9
12
1C
1'
b1 /
1%
#24200
b10 /
#24300
b11 /
#24400
b100 /
#24500
b101 /
0!
#24600
b110 /
#24700
b111 /
#24800
b1000 /
#24900
b1001 /
#25000
0G
00
0Y
b0 /
1!
#25100
b1 /
0%
#25200
b10 /
#25300
b11 /
#25400
b100 /
#25500
b101 /
0!
#25600
b110 /
#25700
b111 /
#25800
b1000 /
#25900
b1001 /
#26000
0Z
10
b0 /
1!
#26100
1?
b100 )
b100 J
b10 "
b10 @
b1 5
b10 3
b10 +
b10 D
b10 L
b10 1
02
0C
0'
1W
b1 /
1%
#26200
b10 /
#26300
b11 /
#26400
b100 /
#26500
b101 /
0!
#26600
b110 /
#26700
b111 /
#26800
b1000 /
#26900
b1001 /
#27000
00
1U
0X
0V
0(
b0 /
1!
#27100
b1 /
0%
#27200
b10 /
#27300
b11 /
#27400
b100 /
#27500
b101 /
0!
#27600
b110 /
#27700
b111 /
#27800
b1000 /
#27900
b1001 /
#28000
1>
1S
10
b0 /
1!
#28100
0?
1T
0W
1R
b1 /
1%
#28200
b10 /
#28300
b11 /
#28400
b100 /
#28500
b101 /
0!
#28600
b110 /
#28700
b111 /
#28800
b1000 /
#28900
b1001 /
#29000
00
0U
1Q
1^
1-
1*
b0 /
1!
#29100
b1 /
0%
#29200
b10 /
#29300
b11 /
#29400
b100 /
#29500
b101 /
0!
#29600
b110 /
#29700
b111 /
#29800
b1000 /
#29900
b1001 /
#30000
1H
0^
0-
0*
0S
1;
1I
10
b0 /
1!
#30100
1P
1]
b1 /
1%
#30200
b10 /
#30300
b11 /
#30400
b100 /
#30500
b101 /
0!
#30600
b110 /
#30700
b111 /
#30800
b1000 /
#30900
b1001 /
#31000
0>
00
0;
0I
1\
0Q
b0 /
1!
#31100
b1 /
0%
#31200
b10 /
#31300
b11 /
#31400
b100 /
#31500
b101 /
0!
#31600
b110 /
#31700
b111 /
#31800
b1000 /
#31900
b1001 /
#32000
10
b0 /
1!
#32100
1G
0T
1[
0R
b1 /
1%
#32200
b10 /
#32300
b11 /
#32400
b100 /
#32500
b101 /
0!
#32600
b110 /
#32700
b111 /
#32800
b1000 /
#32900
b1001 /
#33000
00
1Z
1Y
1V
1(
b0 /
1!
#33100
b1 /
0%
#33200
b10 /
#33300
b11 /
#33400
b100 /
#33500
b101 /
0!
#33600
b110 /
#33700
b111 /
#33800
b1000 /
#33900
b1001 /
#34000
1X
10
b0 /
1!
#34100
b0 5
b11 9
12
1C
1'
0P
b1 /
1%
#34200
b10 /
#34300
b11 /
#34400
b100 /
#34500
b101 /
0!
#34600
b110 /
#34700
b111 /
#34800
b1000 /
#34900
b1001 /
#35000
0H
00
0\
b0 /
1!
#35100
b1 /
0%
#35200
b10 /
#35300
b11 /
#35400
b100 /
#35500
b101 /
0!
#35600
b110 /
#35700
b111 /
#35800
b1000 /
#35900
b1001 /
#36000
10
b0 /
1!
#36100
1?
b110 )
b110 J
b11 "
b11 @
1W
0]
b1 5
b11 3
b11 +
b11 D
b11 L
b11 1
02
0C
0'
b1 /
1%
#36200
b10 /
#36300
b11 /
#36400
b100 /
#36500
b101 /
0!
#36600
b110 /
#36700
b111 /
#36800
b1000 /
#36900
b1001 /
#37000
00
1U
0V
0(
b0 /
1!
#37100
b1 /
0%
#37200
b10 /
#37300
b11 /
#37400
b100 /
#37500
b101 /
0!
#37600
b110 /
#37700
b111 /
#37800
b1000 /
#37900
b1001 /
#38000
1>
1S
10
b0 /
1!
#38100
0?
1R
0[
1T
0W
b1 /
1%
#38200
b10 /
#38300
b11 /
#38400
b100 /
#38500
b101 /
0!
#38600
b110 /
#38700
b111 /
#38800
b1000 /
#38900
b1001 /
#39000
0G
00
0U
1Q
1^
1-
1*
0Y
b0 /
1!
#39100
b1 /
0%
#39200
b10 /
#39300
b11 /
#39400
b100 /
#39500
b101 /
0!
#39600
b110 /
#39700
b111 /
#39800
b1000 /
#39900
b1001 /
#40000
1H
0^
0-
0*
0Z
0S
1;
1I
10
b0 /
1!
#40100
1]
1P
b1 /
1%
#40200
b10 /
#40300
b11 /
#40400
b100 /
#40500
b101 /
0!
#40600
b110 /
#40700
b111 /
#40800
b1000 /
#40900
b1001 /
#41000
0H
0>
00
0;
0I
0X
0\
0Q
b0 /
1!
#41100
b1 /
0%
#41200
b10 /
#41300
b11 /
#41400
b100 /
#41500
b101 /
0!
#41600
b110 /
#41700
b111 /
#41800
b1000 /
#41900
b1001 /
#42000
10
b0 /
1!
#42100
1G
0R
1[
0]
0T
b1 /
1%
#42200
b10 /
#42300
b11 /
#42400
b100 /
#42500
b101 /
0!
#42600
b110 /
#42700
b111 /
#42800
b1000 /
#42900
b1001 /
#43000
00
1Z
1Y
1V
1(
b0 /
1!
#43100
b1 /
0%
#43200
b10 /
#43300
b11 /
#43400
b100 /
#43500
b101 /
0!
#43600
b110 /
#43700
b111 /
#43800
b1000 /
#43900
b1001 /
#44000
1X
10
b0 /
1!
#44100
0[
0P
b0 5
b100 9
12
1C
1'
b1 /
1%
#44200
b10 /
#44300
b11 /
#44400
b100 /
#44500
b101 /
0!
#44600
b110 /
#44700
b111 /
#44800
b1000 /
#44900
b1001 /
#45000
0G
00
0Y
b0 /
1!
#45100
b1 /
0%
#45200
b10 /
#45300
b11 /
#45400
b100 /
#45500
b101 /
0!
#45600
b110 /
#45700
b111 /
#45800
b1000 /
#45900
b1001 /
#46000
0Z
10
b0 /
1!
#46100
1?
b1000 )
b1000 J
b100 "
b100 @
b1 5
b100 3
b100 +
b100 D
b100 L
b100 1
02
0C
0'
1W
b1 /
1%
#46200
b10 /
#46300
b11 /
#46400
b100 /
#46500
b101 /
0!
#46600
b110 /
#46700
b111 /
#46800
b1000 /
#46900
b1001 /
#47000
00
1U
0X
0V
0(
b0 /
1!
#47100
b1 /
0%
#47200
b10 /
#47300
b11 /
#47400
b100 /
#47500
b101 /
0!
#47600
b110 /
#47700
b111 /
#47800
b1000 /
#47900
b1001 /
#48000
1>
1S
10
b0 /
1!
#48100
0?
1T
0W
1R
b1 /
1%
#48200
b10 /
#48300
b11 /
#48400
b100 /
#48500
b101 /
0!
#48600
b110 /
#48700
b111 /
#48800
b1000 /
#48900
b1001 /
#49000
00
0U
1Q
1^
1-
1*
b0 /
1!
#49100
b1 /
0%
#49200
b10 /
#49300
b11 /
#49400
b100 /
#49500
b101 /
0!
#49600
b110 /
#49700
b111 /
#49800
b1000 /
#49900
b1001 /
#50000
1H
0^
0-
0*
0S
1;
1I
10
b0 /
1!
#50100
1P
1]
b1 /
1%
#50200
b10 /
#50300
b11 /
#50400
b100 /
#50500
b101 /
0!
#50600
b110 /
#50700
b111 /
#50800
b1000 /
#50900
b1001 /
#51000
0>
00
0;
0I
1\
0Q
b0 /
1!
#51100
b1 /
0%
#51200
b10 /
#51300
b11 /
#51400
b100 /
#51500
b101 /
0!
#51600
b110 /
#51700
b111 /
#51800
b1000 /
#51900
b1001 /
#52000
10
b0 /
1!
#52100
1G
0T
1[
0R
b1 /
1%
#52200
b10 /
#52300
b11 /
#52400
b100 /
#52500
b101 /
0!
#52600
b110 /
#52700
b111 /
#52800
b1000 /
#52900
b1001 /
#53000
00
1Z
1Y
1V
1(
b0 /
1!
#53100
b1 /
0%
#53200
b10 /
#53300
b11 /
#53400
b100 /
#53500
b101 /
0!
#53600
b110 /
#53700
b111 /
#53800
b1000 /
#53900
b1001 /
#54000
1X
10
b0 /
1!
#54100
b0 5
b101 9
12
1C
1'
0P
b1 /
1%
#54200
b10 /
#54300
b11 /
#54400
b100 /
#54500
b101 /
0!
#54600
b110 /
#54700
b111 /
#54800
b1000 /
#54900
b1001 /
#55000
0H
00
0\
b0 /
1!
#55100
b1 /
0%
#55200
b10 /
#55300
b11 /
#55400
b100 /
#55500
b101 /
0!
#55600
b110 /
#55700
b111 /
#55800
b1000 /
#55900
b1001 /
#56000
10
b0 /
1!
#56100
1?
b1010 )
b1010 J
b101 "
b101 @
1W
0]
b1 5
b101 3
b101 +
b101 D
b101 L
b101 1
02
0C
0'
b1 /
1%
#56200
b10 /
#56300
b11 /
#56400
b100 /
#56500
b101 /
0!
#56600
b110 /
#56700
b111 /
#56800
b1000 /
#56900
b1001 /
#57000
00
1U
0V
0(
b0 /
1!
#57100
b1 /
0%
#57200
b10 /
#57300
b11 /
#57400
b100 /
#57500
b101 /
0!
#57600
b110 /
#57700
b111 /
#57800
b1000 /
#57900
b1001 /
#58000
1>
1S
10
b0 /
1!
#58100
0?
1R
0[
1T
0W
b1 /
1%
#58200
b10 /
#58300
b11 /
#58400
b100 /
#58500
b101 /
0!
#58600
b110 /
#58700
b111 /
#58800
b1000 /
#58900
b1001 /
#59000
0G
00
0U
1Q
1^
1-
1*
0Y
b0 /
1!
#59100
b1 /
0%
#59200
b10 /
#59300
b11 /
#59400
b100 /
#59500
b101 /
0!
#59600
b110 /
#59700
b111 /
#59800
b1000 /
#59900
b1001 /
#60000
1H
0^
0-
0*
0Z
0S
1;
1I
10
b0 /
1!
#60100
1]
1P
b1 /
1%
#60200
b10 /
#60300
b11 /
#60400
b100 /
#60500
b101 /
0!
#60600
b110 /
#60700
b111 /
#60800
b1000 /
#60900
b1001 /
#61000
0H
0>
00
0;
0I
0X
0\
0Q
b0 /
1!
#61100
b1 /
0%
#61200
b10 /
#61300
b11 /
#61400
b100 /
#61500
b101 /
0!
#61600
b110 /
#61700
b111 /
#61800
b1000 /
#61900
b1001 /
#62000
10
b0 /
1!
#62100
1G
0R
1[
0]
0T
b1 /
1%
